<annotation verified="yes">
    <folder>Annotation</folder>
    <filename>00053.jpg</filename>
    <path>Annotation_Adventices-PascalVOC-export/Annotations/00053.jpg</path>
    <source>
        <database>Unknown</database>
    </source>
    <size>
        <width>4896</width>
        <height>2752</height>
        <depth>3</depth>
    </size>
    <segmented>0</segmented>
    <object>
    <name>Lavandin</name>
    <pose>Unspecified</pose>
    <truncated>0</truncated>
    <difficult>0</difficult>
    <bndbox>
        <xmin>404.9323308270677</xmin>
        <ymin>1403.8277591973242</ymin>
        <xmax>1477.0827067669175</xmax>
        <ymax>2273.607023411371</ymax>
    </bndbox>
</object><object>
    <name>Lavandin</name>
    <pose>Unspecified</pose>
    <truncated>0</truncated>
    <difficult>0</difficult>
    <bndbox>
        <xmin>809.8646616541354</xmin>
        <ymin>552.4565217391304</ymin>
        <xmax>1605.9248120300754</xmax>
        <ymax>1210.5434782608695</ymax>
    </bndbox>
</object><object>
    <name>Lavandin</name>
    <pose>Unspecified</pose>
    <truncated>0</truncated>
    <difficult>0</difficult>
    <bndbox>
        <xmin>1072.1503759398497</xmin>
        <ymin>96.85785953177256</ymin>
        <xmax>1684.1503759398497</xmax>
        <ymax>529.4464882943143</ymax>
    </bndbox>
</object><object>
    <name>Lavandin</name>
    <pose>Unspecified</pose>
    <truncated>0</truncated>
    <difficult>0</difficult>
    <bndbox>
        <xmin>2963.3684210526317</xmin>
        <ymin>4.817725752508361</ymin>
        <xmax>3556.9624060150377</xmax>
        <ymax>363.77424749163873</ymax>
    </bndbox>
</object><object>
    <name>Lavandin</name>
    <pose>Unspecified</pose>
    <truncated>0</truncated>
    <difficult>0</difficult>
    <bndbox>
        <xmin>3138.2255639097743</xmin>
        <ymin>386.7842809364548</ymin>
        <xmax>3814.646616541353</xmax>
        <ymax>869.9949832775919</ymax>
    </bndbox>
</object><object>
    <name>Lavandin</name>
    <pose>Unspecified</pose>
    <truncated>0</truncated>
    <difficult>0</difficult>
    <bndbox>
        <xmin>3497.1428571428573</xmin>
        <ymin>911.4130434782608</ymin>
        <xmax>4224.18045112782</xmax>
        <ymax>1500.4698996655516</ymax>
    </bndbox>
</object><object>
    <name>Lavandin</name>
    <pose>Unspecified</pose>
    <truncated>0</truncated>
    <difficult>0</difficult>
    <bndbox>
        <xmin>3879.0676691729323</xmin>
        <ymin>1643.1321070234112</ymin>
        <xmax>4845.383458646616</xmax>
        <ymax>2577.339464882943</ymax>
    </bndbox>
</object><object>
    <name>Adventices</name>
    <pose>Unspecified</pose>
    <truncated>0</truncated>
    <difficult>0</difficult>
    <bndbox>
        <xmin>4693.533834586467</xmin>
        <ymin>980.443143812709</ymin>
        <xmax>4896</xmax>
        <ymax>1256.5635451505016</ymax>
    </bndbox>
</object><object>
    <name>Adventices</name>
    <pose>Unspecified</pose>
    <truncated>0</truncated>
    <difficult>0</difficult>
    <bndbox>
        <xmin>2668.872180451128</xmin>
        <ymin>2379.4531772575247</ymin>
        <xmax>2852.9323308270677</xmax>
        <ymax>2517.513377926421</ymax>
    </bndbox>
</object><object>
    <name>Adventices</name>
    <pose>Unspecified</pose>
    <truncated>0</truncated>
    <difficult>0</difficult>
    <bndbox>
        <xmin>1582.9172932330828</xmin>
        <ymin>2457.6872909698995</ymin>
        <xmax>1895.8195488721806</xmax>
        <ymax>2752</ymax>
    </bndbox>
</object><object>
    <name>Adventices</name>
    <pose>Unspecified</pose>
    <truncated>0</truncated>
    <difficult>0</difficult>
    <bndbox>
        <xmin>27.609022556390975</xmin>
        <ymin>1169.1254180602007</ymin>
        <xmax>197.86466165413535</xmax>
        <ymax>1353.2056856187291</ymax>
    </bndbox>
</object><object>
    <name>Adventices</name>
    <pose>Unspecified</pose>
    <truncated>0</truncated>
    <difficult>0</difficult>
    <bndbox>
        <xmin>13.804511278195488</xmin>
        <ymin>943.6270903010032</ymin>
        <xmax>271.4887218045113</xmax>
        <ymax>1132.3093645484948</ymax>
    </bndbox>
</object><object>
    <name>Adventices</name>
    <pose>Unspecified</pose>
    <truncated>0</truncated>
    <difficult>0</difficult>
    <bndbox>
        <xmin>0</xmin>
        <ymin>492.4631578947368</ymin>
        <xmax>540.7810650887574</xmax>
        <ymax>939.0250836120401</ymax>
    </bndbox>
</object>
</annotation>
