{
    "asset": {
        "format": "jpg",
        "id": "024af604df992acff151dd36f322a0e0",
        "name": "00067.jpg",
        "path": "file:/home/draker/TrainYourOwnYOLO/VOTT/Images_non_modif/00067.jpg",
        "size": {
            "height": 2752,
            "width": 4896
        },
        "state": 2,
        "type": 1
    },
    "regions": [
        {
            "boundingBox": {
                "height": 1040.0535117056854,
                "left": 1877.4135338345864,
                "top": 276.3361204013378,
                "width": 1168.781954887218
            },
            "id": "KrOPZqmqd",
            "points": [
                {
                    "x": 1877.4135338345864,
                    "y": 276.3361204013378
                },
                {
                    "x": 3046.1954887218044,
                    "y": 276.3361204013378
                },
                {
                    "x": 3046.1954887218044,
                    "y": 1316.3896321070233
                },
                {
                    "x": 1877.4135338345864,
                    "y": 1316.3896321070233
                }
            ],
            "tags": [
                "Lavandin"
            ],
            "type": "RECTANGLE"
        },
        {
            "boundingBox": {
                "height": 1306.9698996655518,
                "left": 1743.96992481203,
                "top": 1390.0217391304348,
                "width": 1412.6616541353383
            },
            "id": "KoiSbuX_d",
            "points": [
                {
                    "x": 1743.96992481203,
                    "y": 1390.0217391304348
                },
                {
                    "x": 3156.6315789473683,
                    "y": 1390.0217391304348
                },
                {
                    "x": 3156.6315789473683,
                    "y": 2696.9916387959865
                },
                {
                    "x": 1743.96992481203,
                    "y": 2696.9916387959865
                }
            ],
            "tags": [
                "Lavandin"
            ],
            "type": "RECTANGLE"
        },
        {
            "boundingBox": {
                "height": 138.0602006688963,
                "left": 805.2631578947369,
                "top": 442.00836120401334,
                "width": 161.05263157894737
            },
            "id": "-NfLlZqVu",
            "points": [
                {
                    "x": 805.2631578947369,
                    "y": 442.00836120401334
                },
                {
                    "x": 966.3157894736842,
                    "y": 442.00836120401334
                },
                {
                    "x": 966.3157894736842,
                    "y": 580.0685618729096
                },
                {
                    "x": 805.2631578947369,
                    "y": 580.0685618729096
                }
            ],
            "tags": [
                "Adventices"
            ],
            "type": "RECTANGLE"
        },
        {
            "boundingBox": {
                "height": 174.876254180602,
                "left": 510.76691729323306,
                "top": 685.9147157190635,
                "width": 216.27067669172934
            },
            "id": "aYAw8Y90O",
            "points": [
                {
                    "x": 510.76691729323306,
                    "y": 685.9147157190635
                },
                {
                    "x": 727.0375939849624,
                    "y": 685.9147157190635
                },
                {
                    "x": 727.0375939849624,
                    "y": 860.7909698996655
                },
                {
                    "x": 510.76691729323306,
                    "y": 860.7909698996655
                }
            ],
            "tags": [
                "Adventices"
            ],
            "type": "RECTANGLE"
        },
        {
            "boundingBox": {
                "height": 147.26421404682273,
                "left": 220.8721804511278,
                "top": 589.2725752508361,
                "width": 161.05263157894737
            },
            "id": "9kApOHU5p",
            "points": [
                {
                    "x": 220.8721804511278,
                    "y": 589.2725752508361
                },
                {
                    "x": 381.9248120300752,
                    "y": 589.2725752508361
                },
                {
                    "x": 381.9248120300752,
                    "y": 736.5367892976587
                },
                {
                    "x": 220.8721804511278,
                    "y": 736.5367892976587
                }
            ],
            "tags": [
                "Adventices"
            ],
            "type": "RECTANGLE"
        },
        {
            "boundingBox": {
                "height": 276.1204013377926,
                "left": 3262.466165413534,
                "top": 165.8879598662207,
                "width": 262.2857142857143
            },
            "id": "qdnCeix6q",
            "points": [
                {
                    "x": 3262.466165413534,
                    "y": 165.8879598662207
                },
                {
                    "x": 3524.751879699248,
                    "y": 165.8879598662207
                },
                {
                    "x": 3524.751879699248,
                    "y": 442.00836120401334
                },
                {
                    "x": 3262.466165413534,
                    "y": 442.00836120401334
                }
            ],
            "tags": [
                "Adventices"
            ],
            "type": "RECTANGLE"
        },
        {
            "boundingBox": {
                "height": 202.48829431438125,
                "left": 1288.421052631579,
                "top": 1647.7341137123744,
                "width": 119.6390977443609
            },
            "id": "5ixUjcMfh",
            "points": [
                {
                    "x": 1288.421052631579,
                    "y": 1647.7341137123744
                },
                {
                    "x": 1408.0601503759399,
                    "y": 1647.7341137123744
                },
                {
                    "x": 1408.0601503759399,
                    "y": 1850.2224080267556
                },
                {
                    "x": 1288.421052631579,
                    "y": 1850.2224080267556
                }
            ],
            "tags": [
                "Adventices"
            ],
            "type": "RECTANGLE"
        },
        {
            "boundingBox": {
                "height": 124.25418060200668,
                "left": 1380.451127819549,
                "top": 1979.0785953177256,
                "width": 156.45112781954887
            },
            "id": "-AuSt0Yw9",
            "points": [
                {
                    "x": 1380.451127819549,
                    "y": 1979.0785953177256
                },
                {
                    "x": 1536.9022556390978,
                    "y": 1979.0785953177256
                },
                {
                    "x": 1536.9022556390978,
                    "y": 2103.3327759197323
                },
                {
                    "x": 1380.451127819549,
                    "y": 2103.3327759197323
                }
            ],
            "tags": [
                "Adventices"
            ],
            "type": "RECTANGLE"
        },
        {
            "boundingBox": {
                "height": 110.44816053511704,
                "left": 1026.1353383458647,
                "top": 754.9448160535117,
                "width": 170.25563909774436
            },
            "id": "bRc9dB3AX",
            "points": [
                {
                    "x": 1026.1353383458647,
                    "y": 754.9448160535117
                },
                {
                    "x": 1196.390977443609,
                    "y": 754.9448160535117
                },
                {
                    "x": 1196.390977443609,
                    "y": 865.3929765886287
                },
                {
                    "x": 1026.1353383458647,
                    "y": 865.3929765886287
                }
            ],
            "tags": [
                "Adventices"
            ],
            "type": "RECTANGLE"
        },
        {
            "boundingBox": {
                "height": 635.076923076923,
                "left": 538.375939849624,
                "top": 943.6270903010032,
                "width": 602.796992481203
            },
            "id": "9x_tdlTKH",
            "points": [
                {
                    "x": 538.375939849624,
                    "y": 943.6270903010032
                },
                {
                    "x": 1141.172932330827,
                    "y": 943.6270903010032
                },
                {
                    "x": 1141.172932330827,
                    "y": 1578.7040133779262
                },
                {
                    "x": 538.375939849624,
                    "y": 1578.7040133779262
                }
            ],
            "tags": [
                "Adventices"
            ],
            "type": "RECTANGLE"
        },
        {
            "boundingBox": {
                "height": 555.2280701754386,
                "left": 91.73964497041419,
                "top": 1491.798245614035,
                "width": 535.9526627218935
            },
            "id": "vHCAUaOds",
            "points": [
                {
                    "x": 91.73964497041419,
                    "y": 1491.798245614035
                },
                {
                    "x": 627.6923076923076,
                    "y": 1491.798245614035
                },
                {
                    "x": 627.6923076923076,
                    "y": 2047.0263157894738
                },
                {
                    "x": 91.73964497041419,
                    "y": 2047.0263157894738
                }
            ],
            "tags": [
                "Adventices"
            ],
            "type": "RECTANGLE"
        },
        {
            "boundingBox": {
                "height": 487.6350877192982,
                "left": 154.50887573964496,
                "top": 2216.0087719298244,
                "width": 738.7455621301775
            },
            "id": "d8Lea5IKn",
            "points": [
                {
                    "x": 154.50887573964496,
                    "y": 2216.0087719298244
                },
                {
                    "x": 893.2544378698225,
                    "y": 2216.0087719298244
                },
                {
                    "x": 893.2544378698225,
                    "y": 2703.6438596491225
                },
                {
                    "x": 154.50887573964496,
                    "y": 2703.6438596491225
                }
            ],
            "tags": [
                "Adventices"
            ],
            "type": "RECTANGLE"
        },
        {
            "boundingBox": {
                "height": 255.8877192982456,
                "left": 1530.603550295858,
                "top": 1419.377192982456,
                "width": 207.6213017751479
            },
            "id": "OoYUXp_fi",
            "points": [
                {
                    "x": 1530.603550295858,
                    "y": 1419.377192982456
                },
                {
                    "x": 1738.224852071006,
                    "y": 1419.377192982456
                },
                {
                    "x": 1738.224852071006,
                    "y": 1675.2649122807018
                },
                {
                    "x": 1530.603550295858,
                    "y": 1675.2649122807018
                }
            ],
            "tags": [
                "Adventices"
            ],
            "type": "RECTANGLE"
        },
        {
            "boundingBox": {
                "height": 410.3859649122807,
                "left": 4654.579881656805,
                "top": 1655.9526315789474,
                "width": 241.42011834319527
            },
            "id": "TJBK6n1X4",
            "points": [
                {
                    "x": 4654.579881656805,
                    "y": 1655.9526315789474
                },
                {
                    "x": 4896,
                    "y": 1655.9526315789474
                },
                {
                    "x": 4896,
                    "y": 2066.338596491228
                },
                {
                    "x": 4654.579881656805,
                    "y": 2066.338596491228
                }
            ],
            "tags": [
                "Adventices"
            ],
            "type": "RECTANGLE"
        }
    ],
    "version": "2.1.0"
}