{
    "asset": {
        "format": "JPG",
        "id": "6742369b440e98695c0fdf24db83a91d",
        "name": "P1040412.JPG",
        "path": "file:/home/draker/TrainYourOwnYOLO/Data/Source_Images/Training_Images/P1040412.JPG",
        "size": {
            "width": 4896,
            "height": 2752
        },
        "state": 2,
        "type": 1
    },
    "regions": [
        {
            "id": "e8q5NuI5w",
            "type": "RECTANGLE",
            "tags": [
                "Lavandin"
            ],
            "boundingBox": {
                "height": 1446.745501285347,
                "width": 1475.1676300578033,
                "left": 1556.5317919075144,
                "top": 1290.994858611825
            },
            "points": [
                {
                    "x": 1556.5317919075144,
                    "y": 1290.994858611825
                },
                {
                    "x": 3031.699421965318,
                    "y": 1290.994858611825
                },
                {
                    "x": 3031.699421965318,
                    "y": 2737.7403598971723
                },
                {
                    "x": 1556.5317919075144,
                    "y": 2737.7403598971723
                }
            ]
        },
        {
            "id": "rMcLN9kng",
            "type": "RECTANGLE",
            "tags": [
                "Lavandin"
            ],
            "boundingBox": {
                "height": 1114.241645244216,
                "width": 1040.0462427745665,
                "left": 1683.8843930635837,
                "top": 162.60411311053983
            },
            "points": [
                {
                    "x": 1683.8843930635837,
                    "y": 162.60411311053983
                },
                {
                    "x": 2723.93063583815,
                    "y": 162.60411311053983
                },
                {
                    "x": 2723.93063583815,
                    "y": 1276.8457583547558
                },
                {
                    "x": 1683.8843930635837,
                    "y": 1276.8457583547558
                }
            ]
        }
    ],
    "version": "2.1.0"
}