{
    "asset": {
        "format": "JPG",
        "id": "a6e738d63b22e577a45bed29885ebad8",
        "name": "P1040425.JPG",
        "path": "file:/home/draker/TrainYourOwnYOLO/Data/Source_Images/Training_Images/P1040425.JPG",
        "size": {
            "width": 4896,
            "height": 2752
        },
        "state": 2,
        "type": 1
    },
    "regions": [
        {
            "id": "0Q7A0sNPV",
            "type": "RECTANGLE",
            "tags": [
                "Lavandin"
            ],
            "boundingBox": {
                "height": 1308.7917737789203,
                "width": 1280.6011560693642,
                "left": 1843.0751445086705,
                "top": 1361.740359897172
            },
            "points": [
                {
                    "x": 1843.0751445086705,
                    "y": 1361.740359897172
                },
                {
                    "x": 3123.6763005780344,
                    "y": 1361.740359897172
                },
                {
                    "x": 3123.6763005780344,
                    "y": 2670.5321336760926
                },
                {
                    "x": 1843.0751445086705,
                    "y": 2670.5321336760926
                }
            ]
        },
        {
            "id": "eRtpT7QTg",
            "type": "RECTANGLE",
            "tags": [
                "Lavandin"
            ],
            "boundingBox": {
                "height": 986.8997429305912,
                "width": 1086.0346820809248,
                "left": 1821.849710982659,
                "top": 226.27506426735218
            },
            "points": [
                {
                    "x": 1821.849710982659,
                    "y": 226.27506426735218
                },
                {
                    "x": 2907.8843930635835,
                    "y": 226.27506426735218
                },
                {
                    "x": 2907.8843930635835,
                    "y": 1213.1748071979434
                },
                {
                    "x": 1821.849710982659,
                    "y": 1213.1748071979434
                }
            ]
        }
    ],
    "version": "2.1.0"
}